{"locutions": [], "nodes": [{"text": "ningu\u00e9m que j\u00e1 fumou deixa absolutamente de ser fumador", "type": "I", "nodeID": "176630", "timestamp": "2016-05-31 23:16:35"}, {"text": "nunca se passa a \u201cn\u00e3o-fumador\u201d, mas sim a \u201cex-fumador\u201d", "type": "I", "nodeID": "176632", "timestamp": "2016-05-31 23:16:36"}, {"text": "Default Inference", "nodeID": "176634", "schemeID": "72", "timestamp": "2016-05-31 23:16:36", "scheme": "Default Inference", "type": "RA"}, {"text": "Dizem estes especialistas", "type": "I", "nodeID": "176635", "timestamp": "2016-05-31 23:16:36"}, {"text": "Default Inference", "nodeID": "176637", "schemeID": "72", "timestamp": "2016-05-31 23:16:36", "scheme": "Default Inference", "type": "RA"}], "edges": [{"toID": "176634", "fromID": "176630", "formEdgeID": null, "edgeID": "216165"}, {"toID": "176632", "fromID": "176634", "formEdgeID": null, "edgeID": "216166"}, {"toID": "176637", "fromID": "176635", "formEdgeID": null, "edgeID": "216167"}, {"toID": "176632", "fromID": "176637", "formEdgeID": null, "edgeID": "216168"}]}